sql_magic/__init__.py
sql_magic/connection.py
sql_magic/exceptions.py
sql_magic/notify.py
sql_magic/sql_magic.py
sql_magic/utils.py
sql_magic-0.0.4.dist-info/METADATA
sql_magic-0.0.4.dist-info/RECORD
sql_magic-0.0.4.dist-info/WHEEL
sql_magic-0.0.4.dist-info/top_level.txt
